odoo8_addon_web_context_in_colors-8.0.1.1.0-py2.7-nspkg.pth
odoo_addons/web_context_in_colors/__openerp__.py
odoo_addons/web_context_in_colors/__init__.py
odoo_addons/web_context_in_colors/README.rst
odoo_addons/web_context_in_colors/view/qweb.xml
odoo_addons/web_context_in_colors/static/description/icon.png
odoo_addons/web_context_in_colors/static/src/js/web_context_in_colors.js
odoo8_addon_web_context_in_colors-8.0.1.1.0.dist-info/top_level.txt
odoo8_addon_web_context_in_colors-8.0.1.1.0.dist-info/WHEEL
odoo8_addon_web_context_in_colors-8.0.1.1.0.dist-info/RECORD
odoo8_addon_web_context_in_colors-8.0.1.1.0.dist-info/metadata.json
odoo8_addon_web_context_in_colors-8.0.1.1.0.dist-info/DESCRIPTION.rst
odoo8_addon_web_context_in_colors-8.0.1.1.0.dist-info/METADATA
odoo8_addon_web_context_in_colors-8.0.1.1.0.dist-info/namespace_packages.txt
