Metadata-Version: 2.0
Name: odoo8-addon-web-context-in-colors
Version: 8.0.1.1.0
Summary: Use the context in a tree view's colors and fonts attribute
Home-page: UNKNOWN
Author: UNKNOWN
Author-email: UNKNOWN
License: UNKNOWN
Platform: UNKNOWN
Requires-Dist: odoo (<9.0a,>=8.0a)
Classifier: Programming Language :: Python :: 2.7
Classifier: Framework :: Odoo
